wandb_generic/__init__.py
wandb_generic/checkpointers.py
wandb_generic/loggers.py
wandb_generic/py.typed
wandb_generic/sweeps.py
wandb_generic-1.1.0.dist-info/licenses/LICENSE
wandb_generic-1.1.0.dist-info/METADATA
wandb_generic-1.1.0.dist-info/WHEEL
wandb_generic-1.1.0.dist-info/top_level.txt
wandb_generic-1.1.0.dist-info/RECORD
