Metadata-Version: 2.4
Name: wandb-generic
Version: 1.1.0
Summary: A truly generic Python package for Weights & Biases integration with any ML/DL library or long-running function.
Author-email: Mayukh Sobo <mayukh2012@hotmail.com>
License-Expression: MIT
Project-URL: Homepage, https://github.com/MayukhSobo/wandb-generic
Project-URL: Documentation, https://github.com/MayukhSobo/wandb-generic#readme
Project-URL: Repository, https://github.com/MayukhSobo/wandb-generic
Project-URL: Bug Tracker, https://github.com/MayukhSobo/wandb-generic/issues
Project-URL: Changelog, https://github.com/MayukhSobo/wandb-generic/releases
Project-URL: Source Code, https://github.com/MayukhSobo/wandb-generic
Project-URL: Download, https://pypi.org/project/wandb-generic/
Keywords: wandb,weights-and-biases,machine-learning,deep-learning,experiment-tracking,logging,pytorch,tensorflow,generic,mlops,experiment-management,scientific-computing
Classifier: Development Status :: 5 - Production/Stable
Classifier: Intended Audience :: Developers
Classifier: Intended Audience :: Science/Research
Classifier: Operating System :: OS Independent
Classifier: Programming Language :: Python :: 3
Classifier: Programming Language :: Python :: 3.10
Classifier: Programming Language :: Python :: 3.11
Classifier: Programming Language :: Python :: 3.12
Classifier: Programming Language :: Python :: 3.13
Classifier: Topic :: Scientific/Engineering :: Artificial Intelligence
Classifier: Topic :: Software Development :: Libraries :: Python Modules
Classifier: Topic :: System :: Logging
Classifier: Topic :: Scientific/Engineering
Classifier: Typing :: Typed
Requires-Python: >=3.10
License-File: LICENSE
Requires-Dist: wandb>=0.15.0
Requires-Dist: pyyaml>=6.0
Requires-Dist: numpy>=1.19.0
Provides-Extra: torch
Requires-Dist: torch>=1.9.0; extra == "torch"
Provides-Extra: tensorflow
Requires-Dist: tensorflow>=2.6.0; extra == "tensorflow"
Provides-Extra: dev
Requires-Dist: pytest>=7.0; extra == "dev"
Requires-Dist: pytest-cov>=4.0; extra == "dev"
Requires-Dist: black>=22.0; extra == "dev"
Requires-Dist: isort>=5.10; extra == "dev"
Requires-Dist: mypy>=1.0; extra == "dev"
Requires-Dist: pre-commit>=2.20; extra == "dev"
Provides-Extra: all
Requires-Dist: torch>=1.9.0; extra == "all"
Requires-Dist: tensorflow>=2.6.0; extra == "all"
Dynamic: license-file
